NameVariablePrint/__init__.py
NameVariablePrint/nvprint.py
NameVariablePrint-1.0.0.4.dist-info/METADATA
NameVariablePrint-1.0.0.4.dist-info/WHEEL
NameVariablePrint-1.0.0.4.dist-info/top_level.txt
NameVariablePrint-1.0.0.4.dist-info/RECORD
